forensicstore_stix_schemas.py
forensicstore_stix_schemas-2.1.1.dist-info/LICENSE
forensicstore_stix_schemas-2.1.1.dist-info/METADATA
forensicstore_stix_schemas-2.1.1.dist-info/WHEEL
forensicstore_stix_schemas-2.1.1.dist-info/entry_points.txt
forensicstore_stix_schemas-2.1.1.dist-info/top_level.txt
forensicstore_stix_schemas-2.1.1.dist-info/RECORD
